onegov.recipient-0.0.1-py3.5-nspkg.pth
onegov/recipient/.gitignore
onegov/recipient/__init__.py
onegov/recipient/collection.py
onegov/recipient/model.py
onegov/recipient/upgrade.py
onegov/recipient/tests/conftest.py
onegov/recipient/tests/test_model.py
onegov.recipient-0.0.1.dist-info/DESCRIPTION.rst
onegov.recipient-0.0.1.dist-info/METADATA
onegov.recipient-0.0.1.dist-info/RECORD
onegov.recipient-0.0.1.dist-info/WHEEL
onegov.recipient-0.0.1.dist-info/entry_points.txt
onegov.recipient-0.0.1.dist-info/metadata.json
onegov.recipient-0.0.1.dist-info/namespace_packages.txt
onegov.recipient-0.0.1.dist-info/top_level.txt
