Metadata-Version: 2.0
Name: onegov.recipient
Version: 0.0.1
Summary: A generic recipient model for OneGov Cloud
Home-page: http://github.com/OneGov/onegov.recipient
Author: Seantis GmbH
Author-email: info@seantis.ch
License: GPLv2
Platform: any
Classifier: Intended Audience :: Developers
Classifier: Programming Language :: Python :: 3 :: Only
Classifier: Programming Language :: Python :: 3.4
Classifier: Programming Language :: Python :: 3.5
Classifier: Topic :: Software Development :: Libraries :: Python Modules
Classifier: License :: OSI Approved :: GNU General Public License v2 (GPLv2)
Requires-Dist: onegov.core (>=0.4.0)
Provides-Extra: test
Requires-Dist: coverage; extra == 'test'
Requires-Dist: onegov.testing; extra == 'test'
Requires-Dist: pytest; extra == 'test'
